setup.py
sjb137_probability/__init__.py
sjb137_probability/binomial_distribution.py
sjb137_probability/gaussian_distribution.py
sjb137_probability/general_distribution.py
sjb137_probability.egg-info/PKG-INFO
sjb137_probability.egg-info/SOURCES.txt
sjb137_probability.egg-info/dependency_links.txt
sjb137_probability.egg-info/not-zip-safe
sjb137_probability.egg-info/top_level.txt