Metadata-Version: 1.0
Name: sjb137-probability
Version: 1.37
Summary: Gaussian and Binomial distributions
Home-page: UNKNOWN
Author: Stephen Barrie
Author-email: UNKNOWN
License: UNKNOWN
Platform: UNKNOWN
